odoo/addons/helpdesk_mgmt/README.rst
odoo/addons/helpdesk_mgmt/__init__.py
odoo/addons/helpdesk_mgmt/__manifest__.py
odoo/addons/helpdesk_mgmt/controllers/__init__.py
odoo/addons/helpdesk_mgmt/controllers/main.py
odoo/addons/helpdesk_mgmt/controllers/myaccount.py
odoo/addons/helpdesk_mgmt/data/helpdesk_data.xml
odoo/addons/helpdesk_mgmt/demo/helpdesk_demo.xml
odoo/addons/helpdesk_mgmt/i18n/ca.po
odoo/addons/helpdesk_mgmt/i18n/de.po
odoo/addons/helpdesk_mgmt/i18n/es.po
odoo/addons/helpdesk_mgmt/i18n/es_AR.po
odoo/addons/helpdesk_mgmt/i18n/fr.po
odoo/addons/helpdesk_mgmt/i18n/helpdesk_mgmt.pot
odoo/addons/helpdesk_mgmt/i18n/hu.po
odoo/addons/helpdesk_mgmt/i18n/it.po
odoo/addons/helpdesk_mgmt/i18n/pt.po
odoo/addons/helpdesk_mgmt/i18n/pt_BR.po
odoo/addons/helpdesk_mgmt/i18n/tr.po
odoo/addons/helpdesk_mgmt/migrations/14.0.1.0.0/noupdate_changes.xml
odoo/addons/helpdesk_mgmt/migrations/14.0.1.0.0/post-migration.py
odoo/addons/helpdesk_mgmt/migrations/14.0.1.1.1/noupdate_changes.xml
odoo/addons/helpdesk_mgmt/migrations/14.0.1.1.1/post-migration.py
odoo/addons/helpdesk_mgmt/migrations/14.0.1.17.0/post-migration.py
odoo/addons/helpdesk_mgmt/migrations/14.0.1.4.0/post-migration.py
odoo/addons/helpdesk_mgmt/migrations/14.0.1.4.0/pre-migration.py
odoo/addons/helpdesk_mgmt/migrations/14.0.1.5.1/noupdate_changes.xml
odoo/addons/helpdesk_mgmt/migrations/14.0.1.5.1/post-migration.py
odoo/addons/helpdesk_mgmt/migrations/14.0.1.5.1/pre-migrate.py
odoo/addons/helpdesk_mgmt/migrations/14.0.2.1.0/noupdate_changes.xml
odoo/addons/helpdesk_mgmt/migrations/14.0.2.1.0/post-migration.py
odoo/addons/helpdesk_mgmt/migrations/14.0.2.11.0/noupdate_changes.xml
odoo/addons/helpdesk_mgmt/migrations/14.0.2.11.0/post-migration.py
odoo/addons/helpdesk_mgmt/migrations/14.0.2.4.0/noupdate_changes.xml
odoo/addons/helpdesk_mgmt/migrations/14.0.2.4.0/post-migration.py
odoo/addons/helpdesk_mgmt/models/__init__.py
odoo/addons/helpdesk_mgmt/models/helpdesk_ticket.py
odoo14_addon_helpdesk_mgmt-14.0.2.14.1.dist-info/METADATA
odoo14_addon_helpdesk_mgmt-14.0.2.14.1.dist-info/WHEEL
odoo14_addon_helpdesk_mgmt-14.0.2.14.1.dist-info/top_level.txt
odoo14_addon_helpdesk_mgmt-14.0.2.14.1.dist-info/RECORD
