Metadata-Version: 2.1
Name: odoo14-addon-helpdesk_mgmt
Version: 14.0.2.14.1
Summary: Helpdesk
Home-page: https://github.com/OCA/helpdesk
Author: AdaptiveCity, C2i Change 2 Improve, Domatix, Factor Libre, SDi Soluciones, Odoo Community Association (OCA)
Author-email: support@odoo-community.org
License: AGPL-3
Classifier: Programming Language :: Python
Classifier: Framework :: Odoo
Classifier: Framework :: Odoo :: 14.0
Classifier: License :: OSI Approved :: GNU Affero General Public License v3
Classifier: Development Status :: 4 - Beta
Requires-Python: >=3.6
Requires-Dist: odoo<14.1dev,>=14.0a
